k2s/__init__.py
k2s/bootstrap.py
k2s/cli.py
k2s/conda.py
k2s/env.py
k2s/exceptions.py
k2s/index.py
k2s/parse.py
k2s/spinner.py
k2s/subprocess.py
k2s-0.1.8.dist-info/METADATA
k2s-0.1.8.dist-info/WHEEL
k2s-0.1.8.dist-info/entry_points.txt
k2s-0.1.8.dist-info/top_level.txt
k2s-0.1.8.dist-info/RECORD
